fastyolo/__init__.py
fastyolo/classifier.py
fastyolo/core.py
fastyolo/detector.py
fastyolo/utils.py
fastyolo-0.1.0.dist-info/licenses/LICENSE
fastyolo-0.1.0.dist-info/METADATA
fastyolo-0.1.0.dist-info/WHEEL
fastyolo-0.1.0.dist-info/top_level.txt
fastyolo-0.1.0.dist-info/RECORD
